<annotation>
	<folder>pallet</folder>
	<filename>pallet6.jpg</filename>
	<path>/home/dongho/Desktop/seldat_work/detect_pallet/machine_learning/traning_data/pallet/pallet6.jpg</path>
	<source>
		<database>Unknown</database>
	</source>
	<size>
		<width>400</width>
		<height>325</height>
		<depth>3</depth>
	</size>
	<segmented>0</segmented>
	<object>
		<name>pallet</name>
		<pose>Unspecified</pose>
		<truncated>0</truncated>
		<difficult>0</difficult>
		<bndbox>
			<xmin>21</xmin>
			<ymin>26</ymin>
			<xmax>379</xmax>
			<ymax>292</ymax>
		</bndbox>
	</object>
</annotation>
